[
  { "id": 1, "from": "New York", "to": "Zermatt, Switzerland", "category": "Mountains", "vibe": "Couple", "flight": 850, "hotel": 1200, "food": 600, "activities": 400, "taxi": 150 },
  { "id": 2, "from": "London", "to": "Kyoto, Japan", "category": "City", "vibe": "Family", "flight": 950, "hotel": 1400, "food": 700, "activities": 500, "taxi": 200 },
  { "id": 3, "from": "Mumbai", "to": "Munnar, India", "category": "Forest", "vibe": "Couple", "flight": 120, "hotel": 450, "food": 200, "activities": 150, "taxi": 100 },
  { "id": 4, "from": "Singapore", "to": "Bali, Indonesia", "category": "Beach/Forest", "vibe": "Adventure", "flight": 150, "hotel": 600, "food": 300, "activities": 450, "taxi": 80 },
  { "id": 5, "from": "Dubai", "to": "Nairobi, Kenya", "category": "Forest", "vibe": "Adventure", "flight": 500, "hotel": 900, "food": 400, "activities": 800, "taxi": 300 },
  { "id": 6, "from": "Paris", "to": "Reykjavik, Iceland", "category": "Mountains", "vibe": "Adventure", "flight": 300, "hotel": 1100, "food": 550, "activities": 600, "taxi": 400 },
  { "id": 7, "from": "Sydney", "to": "Queenstown, NZ", "category": "Mountains", "vibe": "Adventure", "flight": 400, "hotel": 1000, "food": 500, "activities": 700, "taxi": 250 },
  { "id": 8, "from": "Berlin", "to": "Black Forest, Germany", "category": "Forest", "vibe": "Family", "flight": 100, "hotel": 700, "food": 450, "activities": 200, "taxi": 180 },
  { "id": 9, "from": "Tokyo", "to": "Seoul, South Korea", "category": "City", "vibe": "Family", "flight": 250, "hotel": 800, "food": 600, "activities": 300, "taxi": 120 },
  { "id": 10, "from": "Los Angeles", "to": "Monteverde, Costa Rica", "category": "Forest", "vibe": "Adventure", "flight": 450, "hotel": 750, "food": 350, "activities": 500, "taxi": 220 },
  { "id": 11, "from": "Toronto", "to": "Banff, Canada", "category": "Mountains", "vibe": "Family", "flight": 350, "hotel": 1300, "food": 500, "activities": 450, "taxi": 300 },
  { "id": 12, "from": "Hong Kong", "to": "Phuket, Thailand", "category": "Beach/Forest", "vibe": "Couple", "flight": 200, "hotel": 500, "food": 250, "activities": 350, "taxi": 90 },
  { "id": 13, "from": "Istanbul", "to": "Cappadocia, Turkey", "category": "Mountains", "vibe": "Couple", "flight": 150, "hotel": 650, "food": 300, "activities": 400, "taxi": 110 },
  { "id": 14, "from": "Madrid", "to": "Rome, Italy", "category": "City", "vibe": "Family", "flight": 180, "hotel": 1100, "food": 650, "activities": 450, "taxi": 140 },
  { "id": 15, "from": "San Francisco", "to": "Yellowstone, USA", "category": "Forest", "vibe": "Family", "flight": 400, "hotel": 950, "food": 450, "activities": 300, "taxi": 500 },
  { "id": 16, "from": "Chicago", "to": "Machu Picchu, Peru", "category": "Mountains", "vibe": "Adventure", "flight": 750, "hotel": 850, "food": 300, "activities": 600, "taxi": 200 },
  { "id": 17, "from": "Cape Town", "to": "Kruger Park, SA", "category": "Forest", "vibe": "Adventure", "flight": 220, "hotel": 1500, "food": 500, "activities": 700, "taxi": 350 },
  { "id": 18, "from": "Amsterdam", "to": "Chamonix, France", "category": "Mountains", "vibe": "Adventure", "flight": 250, "hotel": 1200, "food": 550, "activities": 650, "taxi": 180 },
  { "id": 19, "from": "Bangkok", "to": "Luang Prabang, Laos", "category": "Forest", "vibe": "Solo", "flight": 130, "hotel": 350, "food": 150, "activities": 200, "taxi": 70 },
  { "id": 20, "from": "Delhi", "to": "Leh, Ladakh", "category": "Mountains", "vibe": "Adventure", "flight": 110, "hotel": 400, "food": 200, "activities": 350, "taxi": 400 },
  { "id": 21, "from": "Lisbon", "to": "Azores, Portugal", "category": "Forest/Island", "vibe": "Couple", "flight": 160, "hotel": 850, "food": 400, "activities": 350, "taxi": 200 },
  { "id": 22, "from": "Vancouver", "to": "Whistler, Canada", "category": "Mountains", "vibe": "Family", "flight": 100, "hotel": 1400, "food": 600, "activities": 800, "taxi": 120 },
  { "id": 23, "from": "Vienna", "to": "Hallstatt, Austria", "category": "Mountains/Lake", "vibe": "Couple", "flight": 90, "hotel": 950, "food": 500, "activities": 250, "taxi": 150 },
  { "id": 24, "from": "Sao Paulo", "to": "Iguazu Falls, Brazil", "category": "Forest", "vibe": "Family", "flight": 180, "hotel": 600, "food": 300, "activities": 400, "taxi": 130 },
  { "id": 25, "from": "Riyadh", "to": "Salalah, Oman", "category": "Forest/Mountains", "vibe": "Family", "flight": 280, "hotel": 800, "food": 450, "activities": 300, "taxi": 250 },
  { "id": 26, "from": "Kuala Lumpur", "to": "Borneo, Malaysia", "category": "Forest", "vibe": "Adventure", "flight": 120, "hotel": 550, "food": 200, "activities": 500, "taxi": 180 },
  { "id": 27, "from": "Prague", "to": "Tatra Mountains, Poland", "category": "Mountains", "vibe": "Adventure", "flight": 140, "hotel": 500, "food": 250, "activities": 300, "taxi": 120 },
  { "id": 28, "from": "Moscow", "to": "Lake Baikal, Russia", "category": "Mountains/Nature", "vibe": "Solo", "flight": 300, "hotel": 450, "food": 200, "activities": 400, "taxi": 250 },
  { "id": 29, "from": "Miami", "to": "Cartagena, Colombia", "category": "City/Beach", "vibe": "Couple", "flight": 350, "hotel": 900, "food": 400, "activities": 300, "taxi": 100 },
  { "id": 30, "from": "Cairo", "to": "Aswan, Egypt", "category": "City/History", "vibe": "Family", "flight": 120, "hotel": 600, "food": 250, "activities": 450, "taxi": 80 },
  { "id": 31, "from": "Jakarta", "to": "Komodo Island, Indonesia", "category": "Adventure/Forest", "vibe": "Adventure", "flight": 220, "hotel": 850, "food": 300, "activities": 600, "taxi": 150 },
  { "id": 32, "from": "Oslo", "to": "Lofoten Islands, Norway", "category": "Mountains", "vibe": "Adventure", "flight": 200, "hotel": 1500, "food": 700, "activities": 500, "taxi": 450 },
  { "id": 33, "from": "Zurich", "to": "Interlaken, Swiss", "category": "Mountains", "vibe": "Family", "flight": 100, "hotel": 1800, "food": 800, "activities": 600, "taxi": 200 },
  { "id": 34, "from": "Beijing", "to": "Zhangjiajie, China", "category": "Forest/Mountains", "vibe": "Adventure", "flight": 250, "hotel": 700, "food": 300, "activities": 500, "taxi": 150 },
  { "id": 35, "from": "Melbourne", "to": "Tasmania, Australia", "category": "Forest/Mountains", "vibe": "Adventure", "flight": 150, "hotel": 900, "food": 400, "activities": 450, "taxi": 300 },
  { "id": 36, "from": "Stockholm", "to": "Lapland, Finland", "category": "Forest", "vibe": "Couple", "flight": 210, "hotel": 1600, "food": 600, "activities": 1000, "taxi": 250 },
  { "id": 37, "from": "Athens", "to": "Meteora, Greece", "category": "Mountains", "vibe": "Solo", "flight": 120, "hotel": 450, "food": 250, "activities": 200, "taxi": 180 },
  { "id": 38, "from": "Tel Aviv", "to": "Petra, Jordan", "category": "Adventure/City", "vibe": "Adventure", "flight": 250, "hotel": 700, "food": 350, "activities": 450, "taxi": 200 },
  { "id": 39, "from": "Mexico City", "to": "Oaxaca, Mexico", "category": "City/Forest", "vibe": "Family", "flight": 110, "hotel": 500, "food": 300, "activities": 250, "taxi": 100 },
  { "id": 40, "from": "Buenos Aires", "to": "El Calafate, Argentina", "category": "Mountains", "vibe": "Adventure", "flight": 280, "hotel": 1100, "food": 450, "activities": 700, "taxi": 200 },
  { "id": 41, "from": "Doha", "to": "Baku, Azerbaijan", "category": "City/Mountains", "vibe": "Couple", "flight": 350, "hotel": 850, "food": 400, "activities": 300, "taxi": 150 },
  { "id": 42, "from": "Dublin", "to": "Edinburgh, Scotland", "category": "City/Mountains", "vibe": "Family", "flight": 80, "hotel": 900, "food": 500, "activities": 350, "taxi": 120 },
  { "id": 43, "from": "Brussels", "to": "The Ardennes, Belgium", "category": "Forest", "vibe": "Couple", "flight": 50, "hotel": 600, "food": 400, "activities": 200, "taxi": 100 },
  { "id": 44, "from": "Seoul", "to": "Jeju Island, Korea", "category": "Forest/Mountains", "vibe": "Family", "flight": 100, "hotel": 800, "food": 500, "activities": 400, "taxi": 200 },
  { "id": 45, "from": "Montreal", "to": "Quebec City, Canada", "category": "City", "vibe": "Couple", "flight": 120, "hotel": 1000, "food": 600, "activities": 300, "taxi": 150 },
  { "id": 46, "from": "Santiago", "to": "Atacama Desert, Chile", "category": "Adventure", "vibe": "Adventure", "flight": 200, "hotel": 950, "food": 400, "activities": 600, "taxi": 300 },
  { "id": 47, "from": "Manila", "to": "Palawan, Philippines", "category": "Forest/Beach", "vibe": "Couple", "flight": 140, "hotel": 750, "food": 300, "activities": 500, "taxi": 100 },
  { "id": 48, "from": "Taipei", "to": "Taroko Gorge, Taiwan", "category": "Mountains/Forest", "vibe": "Adventure", "flight": 90, "hotel": 600, "food": 250, "activities": 350, "taxi": 150 },
  { "id": 49, "from": "Helsinki", "to": "Tallinn, Estonia", "category": "City", "vibe": "Solo", "flight": 60, "hotel": 400, "food": 300, "activities": 150, "taxi": 80 },
  { "id": 50, "from": "Auckland", "to": "Rotorua, NZ", "category": "Forest/Geothermal", "vibe": "Family", "flight": 130, "hotel": 700, "food": 400, "activities": 500, "taxi": 200 },
  { "id": 51, "from": "Seattle", "to": "Olympic National Park, USA", "category": "Forest/Mountains", "vibe": "Adventure", "flight": 150, "hotel": 800, "food": 400, "activities": 300, "taxi": 400 },
  { "id": 52, "from": "Boston", "to": "Acadia NP, USA", "category": "Mountains/Forest", "vibe": "Family", "flight": 200, "hotel": 900, "food": 450, "activities": 250, "taxi": 350 },
  { "id": 53, "from": "Dallas", "to": "Aspen, USA", "category": "Mountains", "vibe": "Couple", "flight": 300, "hotel": 2500, "food": 1000, "activities": 1200, "taxi": 300 },
  { "id": 54, "from": "Houston", "to": "Cancun, Mexico", "category": "Beach/Forest", "vibe": "Family", "flight": 250, "hotel": 1500, "food": 800, "activities": 600, "taxi": 150 },
  { "id": 55, "from": "Atlanta", "to": "Savannah, USA", "category": "City", "vibe": "Couple", "flight": 180, "hotel": 800, "food": 500, "activities": 200, "taxi": 120 },
  { "id": 56, "from": "Denver", "to": "Grand Canyon, USA", "category": "Mountains", "vibe": "Adventure", "flight": 220, "hotel": 700, "food": 350, "activities": 400, "taxi": 450 },
  { "id": 57, "from": "Phoenix", "to": "Sedona, USA", "category": "Mountains", "vibe": "Couple", "flight": 100, "hotel": 1200, "food": 600, "activities": 400, "taxi": 180 },
  { "id": 58, "from": "Salt Lake City", "to": "Zion NP, USA", "category": "Mountains", "vibe": "Adventure", "flight": 150, "hotel": 900, "food": 400, "activities": 500, "taxi": 300 },
  { "id": 59, "from": "Portland", "to": "Mt Hood, USA", "category": "Mountains/Forest", "vibe": "Family", "flight": 80, "hotel": 750, "food": 400, "activities": 450, "taxi": 200 },
  { "id": 60, "from": "Vancouver", "to": "Tofino, Canada", "category": "Forest/Beach", "vibe": "Couple", "flight": 250, "hotel": 1400, "food": 700, "activities": 500, "taxi": 200 },
  { "id": 61, "from": "London", "to": "Peak District, UK", "category": "Mountains/Forest", "vibe": "Solo", "flight": 50, "hotel": 500, "food": 350, "activities": 150, "taxi": 100 },
  { "id": 62, "from": "Manchester", "to": "Snowdonia, Wales", "category": "Mountains", "vibe": "Adventure", "flight": 40, "hotel": 550, "food": 300, "activities": 400, "taxi": 150 },
  { "id": 63, "from": "Paris", "to": "Mont Saint-Michel, France", "category": "City/History", "vibe": "Couple", "flight": 100, "hotel": 800, "food": 500, "activities": 250, "taxi": 180 },
  { "id": 64, "from": "Lyon", "to": "Annecy, France", "category": "Mountains/Lake", "vibe": "Family", "flight": 80, "hotel": 1100, "food": 600, "activities": 350, "taxi": 120 },
  { "id": 65, "from": "Nice", "to": "Verdon Gorge, France", "category": "Mountains/Forest", "vibe": "Adventure", "flight": 70, "hotel": 700, "food": 400, "activities": 500, "taxi": 250 },
  { "id": 66, "from": "Munich", "to": "Garmisch, Germany", "category": "Mountains", "vibe": "Adventure", "flight": 60, "hotel": 900, "food": 500, "activities": 600, "taxi": 100 },
  { "id": 67, "from": "Frankfurt", "to": "Mosel Valley, Germany", "category": "Forest/River", "vibe": "Couple", "flight": 90, "hotel": 850, "food": 550, "activities": 300, "taxi": 150 },
  { "id": 68, "from": "Milan", "to": "Lake Como, Italy", "category": "Mountains/Lake", "vibe": "Couple", "flight": 110, "hotel": 2500, "food": 1200, "activities": 800, "taxi": 250 },
  { "id": 69, "from": "Venice", "to": "Dolomites, Italy", "category": "Mountains", "vibe": "Adventure", "flight": 120, "hotel": 1400, "food": 600, "activities": 700, "taxi": 300 },
  { "id": 70, "from": "Florence", "to": "Tuscany, Italy", "category": "Forest/Hills", "vibe": "Couple", "flight": 130, "hotel": 1600, "food": 1000, "activities": 400, "taxi": 250 },
  { "id": 71, "from": "Barcelona", "to": "Pyrenees, Spain", "category": "Mountains", "vibe": "Adventure", "flight": 100, "hotel": 750, "food": 450, "activities": 550, "taxi": 200 },
  { "id": 72, "from": "Madrid", "to": "Sierra Nevada, Spain", "category": "Mountains", "vibe": "Family", "flight": 90, "hotel": 800, "food": 500, "activities": 450, "taxi": 150 },
  { "id": 73, "from": "Geneva", "to": "Zermatt, Switzerland", "category": "Mountains", "vibe": "Adventure", "flight": 80, "hotel": 1800, "food": 900, "activities": 1000, "taxi": 150 },
  { "id": 74, "from": "Zurich", "to": "Lucerne, Switzerland", "category": "Mountains/Lake", "vibe": "Family", "flight": 70, "hotel": 1500, "food": 850, "activities": 500, "taxi": 180 },
  { "id": 75, "from": "Oslo", "to": "Geirangerfjord, Norway", "category": "Mountains/Forest", "vibe": "Couple", "flight": 180, "hotel": 1300, "food": 650, "activities": 700, "taxi": 350 },
  { "id": 76, "from": "Bergen", "to": "Hardangerfjord, Norway", "category": "Mountains/Forest", "vibe": "Adventure", "flight": 140, "hotel": 1100, "food": 600, "activities": 600, "taxi": 300 },
  { "id": 77, "from": "Copenhagen", "to": "Bornholm, Denmark", "category": "Forest/Beach", "vibe": "Family", "flight": 120, "hotel": 900, "food": 550, "activities": 300, "taxi": 200 },
  { "id": 78, "from": "Stockholm", "to": "Gotland, Sweden", "category": "History/Beach", "vibe": "Couple", "flight": 110, "hotel": 1000, "food": 600, "activities": 400, "taxi": 180 },
  { "id": 79, "from": "Helsinki", "to": "Lapland, Finland", "category": "Forest/Snow", "vibe": "Adventure", "flight": 150, "hotel": 1700, "food": 700, "activities": 1200, "taxi": 250 },
  { "id": 80, "from": "Reykjavik", "to": "Akureyri, Iceland", "category": "Mountains", "vibe": "Solo", "flight": 100, "hotel": 850, "food": 500, "activities": 450, "taxi": 300 },
  { "id": 81, "from": "Tokyo", "to": "Hakone, Japan", "category": "Mountains/Forest", "vibe": "Couple", "flight": 80, "hotel": 1200, "food": 600, "activities": 400, "taxi": 120 },
  { "id": 82, "from": "Osaka", "to": "Nara, Japan", "category": "City/Forest", "vibe": "Family", "flight": 60, "hotel": 700, "food": 450, "activities": 250, "taxi": 100 },
  { "id": 83, "from": "Nagoya", "to": "Shirakawa-go, Japan", "category": "Mountains/History", "vibe": "Couple", "flight": 150, "hotel": 600, "food": 350, "activities": 300, "taxi": 200 },
  { "id": 84, "from": "Sapporo", "to": "Niseko, Japan", "category": "Mountains/Snow", "vibe": "Adventure", "flight": 100, "hotel": 1500, "food": 800, "activities": 1000, "taxi": 250 },
  { "id": 85, "from": "Seoul", "to": "Seoraksan, Korea", "category": "Mountains", "vibe": "Adventure", "flight": 90, "hotel": 650, "food": 400, "activities": 300, "taxi": 180 },
  { "id": 86, "from": "Busan", "to": "Gyeongju, Korea", "category": "City/History", "vibe": "Family", "flight": 70, "hotel": 600, "food": 450, "activities": 250, "taxi": 120 },
  { "id": 87, "from": "Bangkok", "to": "Chiang Mai, Thailand", "category": "Mountains/Forest", "vibe": "Adventure", "flight": 80, "hotel": 500, "food": 250, "activities": 400, "taxi": 100 },
  { "id": 88, "from": "Singapore", "to": "Cameron Highlands, Malaysia", "category": "Forest/Hills", "vibe": "Family", "flight": 120, "hotel": 450, "food": 300, "activities": 200, "taxi": 250 },
  { "id": 89, "from": "Ho Chi Minh City", "to": "Da Lat, Vietnam", "category": "Forest/Mountains", "vibe": "Couple", "flight": 70, "hotel": 400, "food": 200, "activities": 250, "taxi": 100 },
  { "id": 90, "from": "Hanoi", "to": "Sapa, Vietnam", "category": "Mountains", "vibe": "Adventure", "flight": 150, "hotel": 350, "food": 180, "activities": 300, "taxi": 150 },
  { "id": 91, "from": "Jakarta", "to": "Yogyakarta, Indonesia", "category": "City/History", "vibe": "Family", "flight": 100, "hotel": 500, "food": 250, "activities": 350, "taxi": 120 },
  { "id": 92, "from": "Mumbai", "to": "Coorg, India", "category": "Forest", "vibe": "Couple", "flight": 150, "hotel": 600, "food": 300, "activities": 350, "taxi": 200 },
  { "id": 93, "from": "Bangalore", "to": "Ooty, India", "category": "Mountains", "vibe": "Family", "flight": 80, "hotel": 450, "food": 250, "activities": 200, "taxi": 180 },
  { "id": 94, "from": "Delhi", "to": "Rishikesh, India", "category": "Mountains/River", "vibe": "Adventure", "flight": 70, "hotel": 300, "food": 150, "activities": 400, "taxi": 120 },
  { "id": 95, "from": "Chennai", "to": "Kodaikanal, India", "category": "Mountains/Forest", "vibe": "Couple", "flight": 100, "hotel": 500, "food": 280, "activities": 220, "taxi": 150 },
  { "id": 96, "from": "Colombo", "to": "Ella, Sri Lanka", "category": "Mountains/Forest", "vibe": "Adventure", "flight": 120, "hotel": 400, "food": 200, "activities": 300, "taxi": 180 },
  { "id": 97, "from": "Male", "to": "Baa Atoll, Maldives", "category": "Beach/Ocean", "vibe": "Couple", "flight": 200, "hotel": 3500, "food": 1500, "activities": 1000, "taxi": 500 },
  { "id": 98, "from": "Kathmandu", "to": "Pokhara, Nepal", "category": "Mountains", "vibe": "Adventure", "flight": 100, "hotel": 350, "food": 200, "activities": 450, "taxi": 100 },
  { "id": 99, "from": "Sydney", "to": "Blue Mountains, Australia", "category": "Mountains/Forest", "vibe": "Family", "flight": 150, "hotel": 800, "food": 450, "activities": 300, "taxi": 120 },
  { "id": 100, "from": "Auckland", "to": "Hobbiton, NZ", "category": "Forest/Fantasy", "vibe": "Family", "flight": 120, "hotel": 700, "food": 400, "activities": 600, "taxi": 150 }
]
